constable/__init__.py
constable-0.3.1.dist-info/LICENSE
constable-0.3.1.dist-info/METADATA
constable-0.3.1.dist-info/WHEEL
constable-0.3.1.dist-info/top_level.txt
constable-0.3.1.dist-info/RECORD
