Metadata-Version: 2.1
Name: constable
Version: 0.3.1
Summary: One decorator for lazy debugging. Inserts print statements directly into your AST.
Home-page: https://github.com/saurabh0719/constable
Author: Saurabh Pujari
Author-email: saurabhpuj99@gmail.com
License: MIT
Project-URL: Documentation, https://github.com/saurabh0719/constable#README
Project-URL: Source, https://github.com/saurabh0719/constable
Keywords: debugger,decorator,tracker,state tracker,variable state,timer
Classifier: Development Status :: 4 - Beta
Classifier: Intended Audience :: Developers
Classifier: License :: OSI Approved :: MIT License
Classifier: Programming Language :: Python
License-File: LICENSE
